[
    {
        "annotations": [
            {
                "class": "obj",
                "height": 102.58823529411768,
                "id": "notebook_0",
                "type": "rect",
                "width": 128.47058823529412,
                "x": 126.58823529411765,
                "y": 295.52941176470586
            },
            {
                "class": "obj",
                "height": 100.59856144057147,
                "id": "cereal_box_0",
                "type": "rect",
                "width": 86.63311408764508,
                "x": 46.630392008923714,
                "y": 166.40185574758056
            },
            {
                "class": "obj",
                "height": 35.76470588235293,
                "id": "keyboard_2",
                "type": "rect",
                "width": 144.94117647058835,
                "x": 0.9411764705882361,
                "y": 262.11764705882376
            },
            {
                "class": "obj",
                "height": 51.967708898566,
                "id": "camera_0",
                "type": "rect",
                "width": 68.73148596261953,
                "x": 35.76272440331423,
                "y": 377.74377651000657
            },
            {
                "class": "obj",
                "height": 39.292614586199704,
                "id": "flashlight_1",
                "type": "rect",
                "width": 30.297919680925077,
                "x": 156.4603508522771,
                "y": 270.31425215325334
            },
            {
                "class": "obj",
                "height": 65.41176470588246,
                "id": "toothpaste_0",
                "type": "rect",
                "width": 36.70588235294123,
                "x": 15.529411764705905,
                "y": 195.76470588235324
            }
        ],
        "class": "image",
        "filename": "img/001.png"
    },
    {
        "annotations": [
            {
                "class": "obj",
                "height": 102.58823529411768,
                "id": "notebook_0",
                "type": "rect",
                "width": 128.47058823529412,
                "x": 152,
                "y": 293
            },
            {
                "class": "obj",
                "height": 99.80822476744697,
                "id": "cereal_box_0",
                "type": "rect",
                "width": 85.83570261217598,
                "x": 77.12185963689579,
                "y": 162.39398920283816
            },
            {
                "class": "obj",
                "height": 36.235342427104115,
                "id": "keyboard_2",
                "type": "rect",
                "width": 147.0590409219688,
                "x": 26,
                "y": 257
            },
            {
                "class": "obj",
                "height": 51.571361428279715,
                "id": "camera_0",
                "type": "rect",
                "width": 67.5424435517605,
                "x": 64.17077976229073,
                "y": 371.5945212054295
            },
            {
                "class": "obj",
                "height": 39.292614586199704,
                "id": "flashlight_1",
                "type": "rect",
                "width": 32.88642067705675,
                "x": 181.7059548171268,
                "y": 266.2353182723756
            },
            {
                "class": "obj",
                "height": 65.21359097073929,
                "id": "toothpaste_0",
                "type": "rect",
                "width": 28.382585476928064,
                "x": 52.89042410859025,
                "y": 192.39634747028634
            },
            {
                "class": "obj",
                "height": 60.350877192982466,
                "id": "kleenex_0",
                "type": "rect",
                "width": 68.30409356725148,
                "x": 0.9356725146198833,
                "y": 194.1520467836258
            },
            {
                "class": "obj",
                "height": 83.27485380116963,
                "id": "greens_1",
                "type": "rect",
                "width": 118.36257309941524,
                "x": 0.0,
                "y": 282.57309941520475
            }
        ],
        "class": "image",
        "filename": "img/002.png"
    },
    {
        "annotations": [
            {
                "class": "obj",
                "height": 96.16146106342461,
                "id": "notebook_0",
                "type": "rect",
                "width": 122.04381400460107,
                "x": 179.79424966551872,
                "y": 291
            },
            {
                "class": "obj",
                "height": 98.68048972060885,
                "id": "cereal_box_0",
                "type": "rect",
                "width": 82.16805491479438,
                "x": 107.90304742979657,
                "y": 160.68658497994187
            },
            {
                "class": "obj",
                "height": 36.235342427104115,
                "id": "keyboard_2",
                "type": "rect",
                "width": 147.0590409219688,
                "x": 51,
                "y": 253
            },
            {
                "class": "obj",
                "height": 48.21826182965731,
                "id": "camera_0",
                "type": "rect",
                "width": 64.18934395313805,
                "x": 92.35309959862245,
                "y": 366
            },
            {
                "class": "obj",
                "height": 37.89548975344036,
                "id": "flashlight_1",
                "type": "rect",
                "width": 30.930445911193658,
                "x": 208.9559747658631,
                "y": 264.39712483275935
            },
            {
                "class": "obj",
                "height": 62.72795960416431,
                "id": "toothpaste_0",
                "type": "rect",
                "width": 27.90913188329474,
                "x": 81.90599214747498,
                "y": 188.71018039044998
            },
            {
                "class": "obj",
                "height": 61.01272531593304,
                "id": "kleenex_0",
                "type": "rect",
                "width": 87.74630594484793,
                "x": 8.675652073784011,
                "y": 189.05872691049757
            },
            {
                "class": "obj",
                "height": 81.45784943203927,
                "id": "greens_1",
                "type": "rect",
                "width": 146.3354373291274,
                "x": 0.5569098559219157,
                "y": 278.7059548171268
            },
            {
                "class": "obj",
                "height": 64.09356725146199,
                "id": "flashlight_0",
                "type": "rect",
                "width": 62.22222222222222,
                "x": 0.4678362573099415,
                "y": 366.31578947368416
            },
            {
                "class": "obj",
                "height": 20.55441671206563,
                "id": "rubber_eraser_1",
                "type": "rect",
                "width": 32.77596178410465,
                "x": 8.888396416028382,
                "y": 458.8634649774652
            },
            {
                "class": "obj",
                "height": 42.13844303429977,
                "id": "cap_0",
                "type": "rect",
                "width": 77.64091078760747,
                "x": 2.322591348347232,
                "y": 167.89017460909992
            }
        ],
        "class": "image",
        "filename": "img/003.png"
    },
    {
        "annotations": [
            {
                "class": "obj",
                "height": 96.16146106342461,
                "id": "notebook_0",
                "type": "rect",
                "width": 122.04381400460107,
                "x": 205,
                "y": 289
            },
            {
                "class": "obj",
                "height": 98.68048972060885,
                "id": "cereal_box_0",
                "type": "rect",
                "width": 82.16805491479438,
                "x": 133,
                "y": 158
            },
            {
                "class": "obj",
                "height": 38.6187239419844,
                "id": "keyboard_2",
                "type": "rect",
                "width": 140.8622489832801,
                "x": 86.48687866547317,
                "y": 247.3316329395838
            },
            {
                "class": "obj",
                "height": 48.21826182965731,
                "id": "camera_0",
                "type": "rect",
                "width": 64.18934395313805,
                "x": 117,
                "y": 360
            },
            {
                "class": "obj",
                "height": 37.89548975344036,
                "id": "flashlight_1",
                "type": "rect",
                "width": 30.930445911193658,
                "x": 234,
                "y": 262
            },
            {
                "class": "obj",
                "height": 62.72795960416431,
                "id": "toothpaste_0",
                "type": "rect",
                "width": 27.90913188329474,
                "x": 73,
                "y": 191
            },
            {
                "class": "obj",
                "height": 61.01272531593304,
                "id": "kleenex_0",
                "type": "rect",
                "width": 87.74630594484793,
                "x": 34,
                "y": 185
            },
            {
                "class": "obj",
                "height": 78.6508318881796,
                "id": "greens_1",
                "type": "rect",
                "width": 172.53426773848415,
                "x": 0.7368421052631575,
                "y": 273.5964912280702
            },
            {
                "class": "obj",
                "height": 58.50506792042455,
                "id": "flashlight_0",
                "type": "rect",
                "width": 76.19347054981576,
                "x": 13.823001337925177,
                "y": 361.1176998662075
            },
            {
                "class": "obj",
                "height": 28.039796829024738,
                "id": "rubber_eraser_1",
                "type": "rect",
                "width": 33.24379804141459,
                "x": 36.33918128654971,
                "y": 451.46783625730995
            },
            {
                "class": "obj",
                "height": 42.13844303429977,
                "id": "cap_0",
                "type": "rect",
                "width": 77.64091078760747,
                "x": 27,
                "y": 166
            },
            {
                "class": "obj",
                "height": 61.28654970760235,
                "id": "notebook_2",
                "type": "rect",
                "width": 116.0233918128655,
                "x": 0.4678362573099415,
                "y": 238.1286549707602
            },
            {
                "class": "obj",
                "height": 28.88728835209227,
                "id": "marker_1",
                "type": "rect",
                "width": 32.22043700810289,
                "x": 0.0,
                "y": 237.76460412875926
            },
            {
                "class": "obj",
                "height": 15.594541910331401,
                "id": "toothbrush_0",
                "type": "rect",
                "width": 41.47484550620051,
                "x": 16.921736966529807,
                "y": 198.74745966571282
            }
        ],
        "class": "image",
        "filename": "img/004.png"
    },
    {
        "annotations": [
            {
                "class": "obj",
                "height": 96.16146106342461,
                "id": "notebook_0",
                "type": "rect",
                "width": 122.04381400460107,
                "x": 230,
                "y": 288
            },
            {
                "class": "obj",
                "height": 97.84221482095325,
                "id": "cereal_box_0",
                "type": "rect",
                "width": 76.85898055030886,
                "x": 166.662173963108,
                "y": 157.11769986620746
            },
            {
                "class": "obj",
                "height": 40.19881712996755,
                "id": "keyboard_2",
                "type": "rect",
                "width": 136.35765922423758,
                "x": 113.28677157887657,
                "y": 244.41461011885463
            },
            {
                "class": "obj",
                "height": 48.21826182965731,
                "id": "camera_0",
                "type": "rect",
                "width": 64.18934395313805,
                "x": 142,
                "y": 355
            },
            {
                "class": "obj",
                "height": 38.72995171221913,
                "id": "flashlight_1",
                "type": "rect",
                "width": 28.42706003485739,
                "x": 259.2679861439213,
                "y": 261.12151280708434
            },
            {
                "class": "obj",
                "height": 62.72795960416431,
                "id": "toothpaste_0",
                "type": "rect",
                "width": 27.90913188329474,
                "x": 140.19316994933246,
                "y": 183.36747543482568
            },
            {
                "class": "obj",
                "height": 54.30652611868814,
                "id": "kleenex_0",
                "type": "rect",
                "width": 80.76068178105118,
                "x": 72.97124832759353,
                "y": 184.63252456517438
            },
            {
                "class": "obj",
                "height": 76.77948685893983,
                "id": "greens_1",
                "type": "rect",
                "width": 200.1366069197707,
                "x": 0.7368421052631522,
                "y": 270.46783625730995
            },
            {
                "class": "obj",
                "height": 57.09315828617093,
                "id": "flashlight_0",
                "type": "rect",
                "width": 75.72283400506454,
                "x": 43.000410630385296,
                "y": 353.11745382099514
            },
            {
                "class": "obj",
                "height": 28.039796829024738,
                "id": "rubber_eraser_1",
                "type": "rect",
                "width": 33.24379804141459,
                "x": 61,
                "y": 443
            },
            {
                "class": "obj",
                "height": 38.22649350257359,
                "id": "cap_0",
                "type": "rect",
                "width": 68.6993118579476,
                "x": 63.73584859517857,
                "y": 163.1617251003444
            },
            {
                "class": "obj",
                "height": 60.81871345029239,
                "id": "notebook_2",
                "type": "rect",
                "width": 138.47953216374268,
                "x": 2.8756584131724026,
                "y": 232.5964912280702
            },
            {
                "class": "obj",
                "height": 28.049013452436668,
                "id": "marker_1",
                "type": "rect",
                "width": 51.780184666733845,
                "x": 10.749326705854585,
                "y": 236.23539973241495
            },
            {
                "class": "obj",
                "height": 13.638567144468311,
                "id": "toothbrush_0",
                "type": "rect",
                "width": 39.79829570688929,
                "x": 48.384544447610544,
                "y": 196.01437583620324
            },
            {
                "class": "obj",
                "height": 33.88307144407986,
                "id": "hand_towel_0",
                "type": "rect",
                "width": 47.27870434057653,
                "x": 1.1819676085144133,
                "y": 185.96290373960102
            },
            {
                "class": "obj",
                "height": 21.92560473924442,
                "id": "camera_1",
                "type": "rect",
                "width": 38.7914545386632,
                "x": 40.33749077027659,
                "y": 208.57434251947893
            }
        ],
        "class": "image",
        "filename": "img/005.png"
    },
    {
        "annotations": [
            {
                "class": "obj",
                "height": 96.16146106342461,
                "id": "notebook_0",
                "type": "rect",
                "width": 122.04381400460107,
                "x": 254,
                "y": 288
            },
            {
                "class": "obj",
                "height": 97.84221482095325,
                "id": "cereal_box_0",
                "type": "rect",
                "width": 74.5363892019616,
                "x": 195.64978640454567,
                "y": 155.66359752809925
            },
            {
                "class": "obj",
                "height": 40.5306158940171,
                "id": "keyboard_2",
                "type": "rect",
                "width": 138.34845180853517,
                "x": 141.317987640496,
                "y": 240.34100617975196
            },
            {
                "class": "obj",
                "height": 48.688898374408495,
                "id": "camera_0",
                "type": "rect",
                "width": 62.7774343188844,
                "x": 168.41190963425365,
                "y": 351
            },
            {
                "class": "obj",
                "height": 38.72995171221913,
                "id": "flashlight_1",
                "type": "rect",
                "width": 28.42706003485739,
                "x": 284,
                "y": 260
            },
            {
                "class": "obj",
                "height": 61.55971286187409,
                "id": "toothpaste_0",
                "type": "rect",
                "width": 25.071961223446998,
                "x": 169.00541740213802,
                "y": 181.33378478351145
            },
            {
                "class": "obj",
                "height": 54.30652611868814,
                "id": "kleenex_0",
                "type": "rect",
                "width": 80.76068178105118,
                "x": 102.17230979389373,
                "y": 181.33243043297705
            },
            {
                "class": "obj",
                "height": 74.78869427464218,
                "id": "greens_1",
                "type": "rect",
                "width": 223.362520403243,
                "x": 2.7740865165277206,
                "y": 266
            },
            {
                "class": "obj",
                "height": 54.975293834790534,
                "id": "flashlight_0",
                "type": "rect",
                "width": 75.25219746031333,
                "x": 70.11786445138046,
                "y": 347.9412730895024
            },
            {
                "class": "obj",
                "height": 28.039796829024738,
                "id": "rubber_eraser_1",
                "type": "rect",
                "width": 33.24379804141459,
                "x": 86,
                "y": 435
            },
            {
                "class": "obj",
                "height": 37.72581632730635,
                "id": "cap_0",
                "type": "rect",
                "width": 68.53241946619184,
                "x": 95.84258806198571,
                "y": 160.4993228247328
            },
            {
                "class": "obj",
                "height": 60.81871345029239,
                "id": "notebook_2",
                "type": "rect",
                "width": 138.47953216374268,
                "x": 28,
                "y": 229
            },
            {
                "class": "obj",
                "height": 28.049013452436668,
                "id": "marker_1",
                "type": "rect",
                "width": 51.780184666733845,
                "x": 43.009480453741446,
                "y": 230.83175325770975
            },
            {
                "class": "obj",
                "height": 13.638567144468311,
                "id": "toothbrush_0",
                "type": "rect",
                "width": 39.79829570688929,
                "x": 77.90759688764133,
                "y": 192.64860865954006
            },
            {
                "class": "obj",
                "height": 33.549286660568356,
                "id": "hand_towel_0",
                "type": "rect",
                "width": 77.82001203187855,
                "x": 0.6337108036606907,
                "y": 183.6662152164885
            },
            {
                "class": "obj",
                "height": 21.92560473924442,
                "id": "camera_1",
                "type": "rect",
                "width": 38.7914545386632,
                "x": 70.67434131969544,
                "y": 204.9986456494655
            },
            {
                "class": "obj",
                "height": 16.84210526315789,
                "id": "scissors_2",
                "type": "rect",
                "width": 55.672514619883096,
                "x": 0.467836257309942,
                "y": 238.1286549707605
            }
        ],
        "class": "image",
        "filename": "img/006.png"
    },
    {
        "annotations": [
            {
                "class": "obj",
                "height": 96.16146106342461,
                "id": "notebook_0",
                "type": "rect",
                "width": 122.04381400460107,
                "x": 278,
                "y": 288
            },
            {
                "class": "obj",
                "height": 97.84221482095325,
                "id": "cereal_box_0",
                "type": "rect",
                "width": 74.5363892019616,
                "x": 221,
                "y": 155
            },
            {
                "class": "obj",
                "height": 40.5306158940171,
                "id": "keyboard_2",
                "type": "rect",
                "width": 138.34845180853517,
                "x": 166,
                "y": 238
            },
            {
                "class": "obj",
                "height": 48.688898374408495,
                "id": "camera_0",
                "type": "rect",
                "width": 62.7774343188844,
                "x": 192,
                "y": 348
            },
            {
                "class": "obj",
                "height": 38.72995171221913,
                "id": "flashlight_1",
                "type": "rect",
                "width": 28.42706003485739,
                "x": 309,
                "y": 260
            },
            {
                "class": "obj",
                "height": 59.3798017752992,
                "id": "toothpaste_0",
                "type": "rect",
                "width": 22.892050136872136,
                "x": 198.55799590829287,
                "y": 180.18904241085903
            },
            {
                "class": "obj",
                "height": 53.31565744297228,
                "id": "kleenex_0",
                "type": "rect",
                "width": 76.79720707818777,
                "x": 132.15251711372238,
                "y": 178.60365252971366
            },
            {
                "class": "obj",
                "height": 74.78869427464218,
                "id": "greens_1",
                "type": "rect",
                "width": 223.362520403243,
                "x": 28,
                "y": 262
            },
            {
                "class": "obj",
                "height": 53.31630001454255,
                "id": "flashlight_0",
                "type": "rect",
                "width": 72.92960611196611,
                "x": 97.32259134834722,
                "y": 343
            },
            {
                "class": "obj",
                "height": 28.039796829024738,
                "id": "rubber_eraser_1",
                "type": "rect",
                "width": 33.24379804141459,
                "x": 111,
                "y": 428
            },
            {
                "class": "obj",
                "height": 37.72581632730635,
                "id": "cap_0",
                "type": "rect",
                "width": 68.53241946619184,
                "x": 125.75022443138181,
                "y": 159.0
            },
            {
                "class": "obj",
                "height": 55.86437007171307,
                "id": "notebook_2",
                "type": "rect",
                "width": 130.75075649315903,
                "x": 65.08859784373342,
                "y": 226.5945212054295
            },
            {
                "class": "obj",
                "height": 24.08553874957326,
                "id": "marker_1",
                "type": "rect",
                "width": 47.42036249358409,
                "x": 74.93608073001097,
                "y": 228.39634747028634
            },
            {
                "class": "obj",
                "height": 14.034914614754655,
                "id": "toothbrush_0",
                "type": "rect",
                "width": 38.01473209060076,
                "x": 109.49777716437193,
                "y": 188.53331733454854
            },
            {
                "class": "obj",
                "height": 33.82871162712024,
                "id": "hand_towel_0",
                "type": "rect",
                "width": 83.40851136291596,
                "x": 26.477598701695044,
                "y": 178.96199664025522
            },
            {
                "class": "obj",
                "height": 20.340214858099074,
                "id": "camera_1",
                "type": "rect",
                "width": 35.62067477637247,
                "x": 102.14338578943831,
                "y": 202.8018262648568
            },
            {
                "class": "obj",
                "height": 19.077504995572866,
                "id": "scissors_2",
                "type": "rect",
                "width": 75.23226227851403,
                "x": 11.028751672406482,
                "y": 232.32345020068877
            },
            {
                "class": "obj",
                "height": 29.4736842105263,
                "id": "calculator_1",
                "type": "rect",
                "width": 65.96491228070175,
                "x": 0.0,
                "y": 247.0175438596491
            },
            {
                "class": "obj",
                "height": 30.877192982456165,
                "id": "notebook_1",
                "type": "rect",
                "width": 94.97076023391813,
                "x": 0.4678362573099415,
                "y": 209.12280701754383
            }
        ],
        "class": "image",
        "filename": "img/007.png"
    },
    {
        "annotations": [
            {
                "class": "obj",
                "height": 89.7346868327316,
                "id": "notebook_0",
                "type": "rect",
                "width": 122.04381400460107,
                "x": 302,
                "y": 289
            },
            {
                "class": "obj",
                "height": 98.17599960446475,
                "id": "cereal_box_0",
                "type": "rect",
                "width": 70.69786419157937,
                "x": 250.00541740213805,
                "y": 154.667569567023
            },
            {
                "class": "obj",
                "height": 40.97705981296377,
                "id": "keyboard_2",
                "type": "rect",
                "width": 130.68561431322638,
                "x": 195.35243606642155,
                "y": 237.0225724159398
            },
            {
                "class": "obj",
                "height": 48.688898374408495,
                "id": "camera_0",
                "type": "rect",
                "width": 62.7774343188844,
                "x": 216,
                "y": 345
            },
            {
                "class": "obj",
                "height": 38.72995171221913,
                "id": "flashlight_1",
                "type": "rect",
                "width": 28.42706003485739,
                "x": 334,
                "y": 260
            },
            {
                "class": "obj",
                "height": 59.3798017752992,
                "id": "toothpaste_0",
                "type": "rect",
                "width": 22.892050136872136,
                "x": 225.16824674229025,
                "y": 178.50067717526724
            },
            {
                "class": "obj",
                "height": 53.31565744297228,
                "id": "kleenex_0",
                "type": "rect",
                "width": 76.79720707818777,
                "x": 160.52977408563405,
                "y": 178.64722790662924
            },
            {
                "class": "obj",
                "height": 71.74434153525357,
                "id": "greens_1",
                "type": "rect",
                "width": 223.362520403243,
                "x": 53.0,
                "y": 259.64722790662927
            },
            {
                "class": "obj",
                "height": 53.31630001454255,
                "id": "flashlight_0",
                "type": "rect",
                "width": 72.92960611196611,
                "x": 121,
                "y": 339
            },
            {
                "class": "obj",
                "height": 28.039796829024738,
                "id": "rubber_eraser_1",
                "type": "rect",
                "width": 33.24379804141459,
                "x": 137.51482469896683,
                "y": 421.44115006689617
            },
            {
                "class": "obj",
                "height": 36.88754142765072,
                "id": "cap_0",
                "type": "rect",
                "width": 68.8118444327437,
                "x": 154.07367463207058,
                "y": 157.1617251003444
            },
            {
                "class": "obj",
                "height": 55.02609517205744,
                "id": "notebook_2",
                "type": "rect",
                "width": 126.83880696143285,
                "x": 93.91194953172618,
                "y": 224
            },
            {
                "class": "obj",
                "height": 24.08553874957326,
                "id": "marker_1",
                "type": "rect",
                "width": 47.42036249358409,
                "x": 102.58850099613164,
                "y": 224.05872691049763
            },
            {
                "class": "obj",
                "height": 14.034914614754655,
                "id": "toothbrush_0",
                "type": "rect",
                "width": 34.94105745853018,
                "x": 140.44384324347786,
                "y": 186.94070120413264
            },
            {
                "class": "obj",
                "height": 32.431586794360896,
                "id": "hand_towel_0",
                "type": "rect",
                "width": 81.45253659705287,
                "x": 57.706199197244885,
                "y": 175.8823001337925
            },
            {
                "class": "obj",
                "height": 20.340214858099074,
                "id": "camera_1",
                "type": "rect",
                "width": 35.62067477637247,
                "x": 131.23572890276094,
                "y": 198.6468172762439
            },
            {
                "class": "obj",
                "height": 19.077504995572866,
                "id": "scissors_2",
                "type": "rect",
                "width": 73.34971609950918,
                "x": 43.05621032343305,
                "y": 227.33243043297702
            },
            {
                "class": "obj",
                "height": 29.4736842105263,
                "id": "calculator_1",
                "type": "rect",
                "width": 67.3620371134611,
                "x": 29.57379765467674,
                "y": 241.4557702832176
            },
            {
                "class": "obj",
                "height": 31.52425630391241,
                "id": "notebook_1",
                "type": "rect",
                "width": 115.2519906420899,
                "x": 8.248543677462312,
                "y": 205.70595481712684
            }
        ],
        "class": "image",
        "filename": "img/008.png"
    },
    {
        "annotations": [
            {
                "class": "obj",
                "height": 89.7346868327316,
                "id": "notebook_0",
                "type": "rect",
                "width": 122.04381400460107,
                "x": 326,
                "y": 291
            },
            {
                "class": "obj",
                "height": 97.70536305971356,
                "id": "cereal_box_0",
                "type": "rect",
                "width": 68.81531801257451,
                "x": 276.88254617900486,
                "y": 155
            },
            {
                "class": "obj",
                "height": 43.33024253671982,
                "id": "keyboard_2",
                "type": "rect",
                "width": 129.03838640659717,
                "x": 221.17659136187802,
                "y": 235.05872691049757
            },
            {
                "class": "obj",
                "height": 42.347338849827,
                "id": "camera_0",
                "type": "rect",
                "width": 60.795696967452656,
                "x": 241.78356361628855,
                "y": 345.37808482171806
            },
            {
                "class": "obj",
                "height": 38.72995171221913,
                "id": "flashlight_1",
                "type": "rect",
                "width": 28.42706003485739,
                "x": 358,
                "y": 260
            },
            {
                "class": "obj",
                "height": 59.3798017752992,
                "id": "toothpaste_0",
                "type": "rect",
                "width": 22.892050136872136,
                "x": 251.64722790662927,
                "y": 177.52936345524876
            },
            {
                "class": "obj",
                "height": 53.31565744297228,
                "id": "kleenex_0",
                "type": "rect",
                "width": 76.79720707818777,
                "x": 188.97260602714752,
                "y": 176.4054787945705
            },
            {
                "class": "obj",
                "height": 70.06779173594236,
                "id": "greens_1",
                "type": "rect",
                "width": 216.93574617254998,
                "x": 83.02964939793367,
                "y": 257
            },
            {
                "class": "obj",
                "height": 47.569261695390594,
                "id": "flashlight_0",
                "type": "rect",
                "width": 67.5789152631005,
                "x": 151.74703831915195,
                "y": 335.99086867571583
            },
            {
                "class": "obj",
                "height": 28.039796829024738,
                "id": "rubber_eraser_1",
                "type": "rect",
                "width": 33.24379804141459,
                "x": 163,
                "y": 415
            },
            {
                "class": "obj",
                "height": 36.88754142765072,
                "id": "cap_0",
                "type": "rect",
                "width": 65.04654346502346,
                "x": 183.9543433785793,
                "y": 155.0091313242842
            },
            {
                "class": "obj",
                "height": 55.02609517205744,
                "id": "notebook_2",
                "type": "rect",
                "width": 126.83880696143285,
                "x": 122.05913754088289,
                "y": 220.5880903657464
            },
            {
                "class": "obj",
                "height": 22.698322603571057,
                "id": "marker_1",
                "type": "rect",
                "width": 46.03314634758192,
                "x": 131.96347470286338,
                "y": 222.59452120542954
            },
            {
                "class": "obj",
                "height": 14.034914614754655,
                "id": "toothbrush_0",
                "type": "rect",
                "width": 34.94105745853018,
                "x": 167.7142135480834,
                "y": 185.09131324284144
            },
            {
                "class": "obj",
                "height": 32.82793426464724,
                "id": "hand_towel_0",
                "type": "rect",
                "width": 76.69636695361677,
                "x": 90.13425446515416,
                "y": 172.81095758914094
            },
            {
                "class": "obj",
                "height": 19.151172447240043,
                "id": "camera_1",
                "type": "rect",
                "width": 33.83711116008392,
                "x": 160.55799590829295,
                "y": 197.39634747028634
            },
            {
                "class": "obj",
                "height": 17.29394137928432,
                "id": "scissors_2",
                "type": "rect",
                "width": 71.1698050129343,
                "x": 72.95434337857927,
                "y": 224.18904241085903
            },
            {
                "class": "obj",
                "height": 29.4736842105263,
                "id": "calculator_1",
                "type": "rect",
                "width": 67.3620371134611,
                "x": 58.765092358009696,
                "y": 236.76468172762438
            },
            {
                "class": "obj",
                "height": 28.947997747051176,
                "id": "notebook_1",
                "type": "rect",
                "width": 110.29764726351063,
                "x": 41.323296876013174,
                "y": 202.79269494057272
            }
        ],
        "class": "image",
        "filename": "img/009.png"
    },
    {
        "annotations": [
            {
                "class": "obj",
                "height": 84.55768484046826,
                "id": "notebook_0",
                "type": "rect",
                "width": 122.74976882172791,
                "x": 349.05872691049757,
                "y": 294.4119096342536
            },
            {
                "class": "obj",
                "height": 97.70536305971356,
                "id": "cereal_box_0",
                "type": "rect",
                "width": 70.93318246395496,
                "x": 302,
                "y": 155
            },
            {
                "class": "obj",
                "height": 43.33024253671982,
                "id": "keyboard_2",
                "type": "rect",
                "width": 129.03838640659717,
                "x": 247.8825461790048,
                "y": 233.58809036574638
            },
            {
                "class": "obj",
                "height": 42.347338849827,
                "id": "camera_0",
                "type": "rect",
                "width": 60.795696967452656,
                "x": 266,
                "y": 344
            },
            {
                "class": "obj",
                "height": 40.61249789122394,
                "id": "flashlight_1",
                "type": "rect",
                "width": 29.13301485198423,
                "x": 383,
                "y": 261
            },
            {
                "class": "obj",
                "height": 59.3798017752992,
                "id": "toothpaste_0",
                "type": "rect",
                "width": 22.892050136872136,
                "x": 277,
                "y": 178
            },
            {
                "class": "obj",
                "height": 53.31565744297228,
                "id": "kleenex_0",
                "type": "rect",
                "width": 76.79720707818777,
                "x": 214,
                "y": 175
            },
            {
                "class": "obj",
                "height": 69.83247346356671,
                "id": "greens_1",
                "type": "rect",
                "width": 213.1706538145403,
                "x": 111.76509235800968,
                "y": 255
            },
            {
                "class": "obj",
                "height": 47.569261695390594,
                "id": "flashlight_0",
                "type": "rect",
                "width": 67.5789152631005,
                "x": 177,
                "y": 332
            },
            {
                "class": "obj",
                "height": 26.157250650019876,
                "id": "rubber_eraser_1",
                "type": "rect",
                "width": 30.419978772907328,
                "x": 187,
                "y": 411.88254617900486
            },
            {
                "class": "obj",
                "height": 36.88754142765072,
                "id": "cap_0",
                "type": "rect",
                "width": 65.04654346502346,
                "x": 211.82381926850724,
                "y": 155.0
            },
            {
                "class": "obj",
                "height": 55.02609517205744,
                "id": "notebook_2",
                "type": "rect",
                "width": 126.83880696143285,
                "x": 151.0004106303853,
                "y": 218.2940451828732
            },
            {
                "class": "obj",
                "height": 22.698322603571057,
                "id": "marker_1",
                "type": "rect",
                "width": 46.03314634758192,
                "x": 157,
                "y": 221
            },
            {
                "class": "obj",
                "height": 14.034914614754655,
                "id": "toothbrush_0",
                "type": "rect",
                "width": 34.94105745853018,
                "x": 195.24065646738444,
                "y": 183.35195083260015
            },
            {
                "class": "obj",
                "height": 32.82793426464724,
                "id": "hand_towel_0",
                "type": "rect",
                "width": 76.69636695361677,
                "x": 119.47104717513653,
                "y": 171.47063654475122
            },
            {
                "class": "obj",
                "height": 19.151172447240043,
                "id": "camera_1",
                "type": "rect",
                "width": 33.83711116008392,
                "x": 186,
                "y": 195
            },
            {
                "class": "obj",
                "height": 17.29394137928432,
                "id": "scissors_2",
                "type": "rect",
                "width": 71.1698050129343,
                "x": 101.52977408563409,
                "y": 221.47063654475116
            },
            {
                "class": "obj",
                "height": 29.4736842105263,
                "id": "calculator_1",
                "type": "rect",
                "width": 67.3620371134611,
                "x": 88.23572890276091,
                "y": 232.823408638122
            },
            {
                "class": "obj",
                "height": 27.536088112797557,
                "id": "notebook_1",
                "type": "rect",
                "width": 107.94446453975456,
                "x": 70.70636544751211,
                "y": 200
            }
        ],
        "class": "image",
        "filename": "img/010.png"
    },
    {
        "annotations": [
            {
                "class": "obj",
                "height": 87.85214065372674,
                "id": "notebook_0",
                "type": "rect",
                "width": 124.16167845598159,
                "x": 373,
                "y": 296
            },
            {
                "class": "obj",
                "height": 98.8944054705726,
                "id": "cereal_box_0",
                "type": "rect",
                "width": 66.1770128205189,
                "x": 331.3598221731498,
                "y": 153.6127838539978
            },
            {
                "class": "obj",
                "height": 46.3028485638674,
                "id": "keyboard_2",
                "type": "rect",
                "width": 129.23656014174037,
                "x": 273.99086867571583,
                "y": 233.99999999999997
            },
            {
                "class": "obj",
                "height": 42.347338849827,
                "id": "camera_0",
                "type": "rect",
                "width": 60.795696967452656,
                "x": 289,
                "y": 344
            },
            {
                "class": "obj",
                "height": 40.61249789122394,
                "id": "flashlight_1",
                "type": "rect",
                "width": 29.13301485198423,
                "x": 408,
                "y": 263
            },
            {
                "class": "obj",
                "height": 59.3798017752992,
                "id": "toothpaste_0",
                "type": "rect",
                "width": 22.892050136872136,
                "x": 302,
                "y": 178
            },
            {
                "class": "obj",
                "height": 53.31565744297228,
                "id": "kleenex_0",
                "type": "rect",
                "width": 76.79720707818777,
                "x": 241.17991108657486,
                "y": 174.39634747028634
            },
            {
                "class": "obj",
                "height": 69.83247346356671,
                "id": "greens_1",
                "type": "rect",
                "width": 213.1706538145403,
                "x": 137,
                "y": 253
            },
            {
                "class": "obj",
                "height": 47.569261695390594,
                "id": "flashlight_0",
                "type": "rect",
                "width": 67.5789152631005,
                "x": 200,
                "y": 330
            },
            {
                "class": "obj",
                "height": 26.157250650019876,
                "id": "rubber_eraser_1",
                "type": "rect",
                "width": 30.419978772907328,
                "x": 211,
                "y": 408
            },
            {
                "class": "obj",
                "height": 36.689367692507545,
                "id": "cap_0",
                "type": "rect",
                "width": 65.4428909353098,
                "x": 238.98173735143166,
                "y": 153.81095758914103
            },
            {
                "class": "obj",
                "height": 55.02609517205744,
                "id": "notebook_2",
                "type": "rect",
                "width": 126.83880696143285,
                "x": 176,
                "y": 216
            },
            {
                "class": "obj",
                "height": 22.698322603571057,
                "id": "marker_1",
                "type": "rect",
                "width": 46.03314634758192,
                "x": 182,
                "y": 219
            },
            {
                "class": "obj",
                "height": 14.034914614754655,
                "id": "toothbrush_0",
                "type": "rect",
                "width": 34.94105745853018,
                "x": 221.93064993179482,
                "y": 181.48766071312784
            },
            {
                "class": "obj",
                "height": 29.458980767213347,
                "id": "hand_towel_0",
                "type": "rect",
                "width": 74.31828213189871,
                "x": 148.55799590829284,
                "y": 171.17991108657486
            },
            {
                "class": "obj",
                "height": 19.151172447240043,
                "id": "camera_1",
                "type": "rect",
                "width": 33.83711116008392,
                "x": 213.57625855686118,
                "y": 193.40547879457048
            },
            {
                "class": "obj",
                "height": 13.924987881850399,
                "id": "scissors_2",
                "type": "rect",
                "width": 68.39537272092993,
                "x": 132.15251711372238,
                "y": 220.97260602714755
            },
            {
                "class": "obj",
                "height": 25.31203577251972,
                "id": "calculator_1",
                "type": "rect",
                "width": 62.40769373488183,
                "x": 117.7561696434361,
                "y": 231.9817373514317
            },
            {
                "class": "obj",
                "height": 25.55435076136584,
                "id": "notebook_1",
                "type": "rect",
                "width": 105.36820598289333,
                "x": 101.54886458400878,
                "y": 197.7926949405727
            }
        ],
        "class": "image",
        "filename": "img/011.png"
    },
    {
        "annotations": [
            {
                "class": "obj",
                "height": 92.08786955648765,
                "id": "notebook_0",
                "type": "rect",
                "width": 124.39699672835712,
                "x": 396.76468172762446,
                "y": 296.88213554861954
            },
            {
                "class": "obj",
                "height": 98.18845065344581,
                "id": "cereal_box_0",
                "type": "rect",
                "width": 69.47146863377738,
                "x": 357.176591361878,
                "y": 154
            },
            {
                "class": "obj",
                "height": 46.3028485638674,
                "id": "keyboard_2",
                "type": "rect",
                "width": 129.23656014174037,
                "x": 299,
                "y": 234
            },
            {
                "class": "obj",
                "height": 42.347338849827,
                "id": "camera_0",
                "type": "rect",
                "width": 60.795696967452656,
                "x": 313,
                "y": 344
            },
            {
                "class": "obj",
                "height": 40.61249789122394,
                "id": "flashlight_1",
                "type": "rect",
                "width": 29.13301485198423,
                "x": 433,
                "y": 265
            },
            {
                "class": "obj",
                "height": 58.95815553031372,
                "id": "toothpaste_0",
                "type": "rect",
                "width": 20.081075170302334,
                "x": 332.2003036881541,
                "y": 177.29725625835755
            },
            {
                "class": "obj",
                "height": 53.1751086946438,
                "id": "kleenex_0",
                "type": "rect",
                "width": 70.47251340340571,
                "x": 269.7948162048693,
                "y": 174.82713372827038
            },
            {
                "class": "obj",
                "height": 67.00865419505942,
                "id": "greens_1",
                "type": "rect",
                "width": 205.87578737089652,
                "x": 167.1770019922633,
                "y": 254.8238192685073
            },
            {
                "class": "obj",
                "height": 47.569261695390594,
                "id": "flashlight_0",
                "type": "rect",
                "width": 67.5789152631005,
                "x": 224,
                "y": 328
            },
            {
                "class": "obj",
                "height": 26.157250650019876,
                "id": "rubber_eraser_1",
                "type": "rect",
                "width": 30.419978772907328,
                "x": 234,
                "y": 405
            },
            {
                "class": "obj",
                "height": 35.56497770587961,
                "id": "cap_0",
                "type": "rect",
                "width": 61.92917222709755,
                "x": 266.38932872158426,
                "y": 153.43780500668606
            },
            {
                "class": "obj",
                "height": 55.02609517205744,
                "id": "notebook_2",
                "type": "rect",
                "width": 126.83880696143285,
                "x": 201,
                "y": 215
            },
            {
                "class": "obj",
                "height": 20.168445133658253,
                "id": "marker_1",
                "type": "rect",
                "width": 43.222171381012146,
                "x": 215.01127865472392,
                "y": 216.99999999999997
            },
            {
                "class": "obj",
                "height": 14.87820710472559,
                "id": "toothbrush_0",
                "type": "rect",
                "width": 32.97337498193134,
                "x": 249.927123180015,
                "y": 180.84817259694756
            },
            {
                "class": "obj",
                "height": 27.912944535599962,
                "id": "hand_towel_0",
                "type": "rect",
                "width": 70.94511217201497,
                "x": 179.20030368815412,
                "y": 170.14054874832848
            },
            {
                "class": "obj",
                "height": 17.745684963955142,
                "id": "camera_1",
                "type": "rect",
                "width": 31.166684941842632,
                "x": 241.6704262182413,
                "y": 193.4054874832849
            },
            {
                "class": "obj",
                "height": 13.362792888536433,
                "id": "scissors_2",
                "type": "rect",
                "width": 65.02220276104619,
                "x": 160.37316995988374,
                "y": 219
            },
            {
                "class": "obj",
                "height": 24.047097037563304,
                "id": "calculator_1",
                "type": "rect",
                "width": 59.03452377499809,
                "x": 146.37316995988374,
                "y": 229
            },
            {
                "class": "obj",
                "height": 26.819289496322256,
                "id": "notebook_1",
                "type": "rect",
                "width": 102.97887726130901,
                "x": 131.49755994651167,
                "y": 195.0161587617006
            }
        ],
        "class": "image",
        "filename": "img/012.png"
    },
    {
        "annotations": [
            {
                "class": "obj",
                "height": 95.61764364212172,
                "id": "notebook_0",
                "type": "rect",
                "width": 127.6914525416156,
                "x": 422.2353182723756,
                "y": 299.11745382099514
            },
            {
                "class": "obj",
                "height": 100.14764417436373,
                "id": "cereal_box_0",
                "type": "rect",
                "width": 70.10615235562751,
                "x": 383.88254617900486,
                "y": 154.2940451828732
            },
            {
                "class": "obj",
                "height": 50.06794092187707,
                "id": "keyboard_2",
                "type": "rect",
                "width": 132.76633422737444,
                "x": 322.823408638122,
                "y": 233.29404518287316
            },
            {
                "class": "obj",
                "height": 42.347338849827,
                "id": "camera_0",
                "type": "rect",
                "width": 60.795696967452656,
                "x": 337,
                "y": 345
            },
            {
                "class": "obj",
                "height": 42.730362342604394,
                "id": "flashlight_1",
                "type": "rect",
                "width": 26.77983212822818,
                "x": 463.17700199226323,
                "y": 267.0
            },
            {
                "class": "obj",
                "height": 58.95815553031372,
                "id": "toothpaste_0",
                "type": "rect",
                "width": 20.081075170302334,
                "x": 357,
                "y": 177
            },
            {
                "class": "obj",
                "height": 53.1751086946438,
                "id": "kleenex_0",
                "type": "rect",
                "width": 70.47251340340571,
                "x": 295,
                "y": 175
            },
            {
                "class": "obj",
                "height": 67.00865419505942,
                "id": "greens_1",
                "type": "rect",
                "width": 205.87578737089652,
                "x": 192,
                "y": 255
            },
            {
                "class": "obj",
                "height": 42.15694143075166,
                "id": "flashlight_0",
                "type": "rect",
                "width": 65.69636908409564,
                "x": 249.41190963425362,
                "y": 327.88254617900486
            },
            {
                "class": "obj",
                "height": 26.157250650019876,
                "id": "rubber_eraser_1",
                "type": "rect",
                "width": 30.419978772907328,
                "x": 257,
                "y": 403
            },
            {
                "class": "obj",
                "height": 35.56497770587961,
                "id": "cap_0",
                "type": "rect",
                "width": 61.92917222709755,
                "x": 291.9838412382994,
                "y": 152.85945125167152
            },
            {
                "class": "obj",
                "height": 47.96654700078929,
                "id": "notebook_2",
                "type": "rect",
                "width": 117.19075779403306,
                "x": 232.11827508176572,
                "y": 217.29445581325848
            },
            {
                "class": "obj",
                "height": 20.168445133658253,
                "id": "marker_1",
                "type": "rect",
                "width": 43.222171381012146,
                "x": 240.98384123829942,
                "y": 215.01615876170058
            },
            {
                "class": "obj",
                "height": 14.87820710472559,
                "id": "toothbrush_0",
                "type": "rect",
                "width": 32.97337498193134,
                "x": 276.6865849799418,
                "y": 179.85945125167152
            },
            {
                "class": "obj",
                "height": 28.334590780585415,
                "id": "hand_towel_0",
                "type": "rect",
                "width": 71.64785591365742,
                "x": 205.68658497994187,
                "y": 169.0
            },
            {
                "class": "obj",
                "height": 17.886233712283627,
                "id": "camera_1",
                "type": "rect",
                "width": 32.009977431813596,
                "x": 267.4216462449855,
                "y": 192.70274374164242
            },
            {
                "class": "obj",
                "height": 13.362792888536433,
                "id": "scissors_2",
                "type": "rect",
                "width": 65.02220276104619,
                "x": 188.37316995988377,
                "y": 216.71890250334303
            },
            {
                "class": "obj",
                "height": 23.105823948060873,
                "id": "calculator_1",
                "type": "rect",
                "width": 59.03452377499809,
                "x": 174.7650923580097,
                "y": 227.00000000000006
            },
            {
                "class": "obj",
                "height": 26.67874074799377,
                "id": "notebook_1",
                "type": "rect",
                "width": 102.27613351966656,
                "x": 159.65426745654077,
                "y": 192.99999999999997
            }
        ],
        "class": "image",
        "filename": "img/013.png"
    },
    {
        "annotations": [
            {
                "class": "obj",
                "height": 99.26743004666736,
                "id": "notebook_0",
                "type": "rect",
                "width": 130.67764141806197,
                "x": 447,
                "y": 303
            },
            {
                "class": "obj",
                "height": 102.12938152579545,
                "id": "cereal_box_0",
                "type": "rect",
                "width": 73.67327958820455,
                "x": 409,
                "y": 154.00913132428414
            },
            {
                "class": "obj",
                "height": 50.06794092187707,
                "id": "keyboard_2",
                "type": "rect",
                "width": 132.76633422737444,
                "x": 348,
                "y": 234
            },
            {
                "class": "obj",
                "height": 42.347338849827,
                "id": "camera_0",
                "type": "rect",
                "width": 60.795696967452656,
                "x": 361,
                "y": 347
            },
            {
                "class": "obj",
                "height": 42.730362342604394,
                "id": "flashlight_1",
                "type": "rect",
                "width": 26.44803336417857,
                "x": 490.98618887644636,
                "y": 270.99079258429765
            },
            {
                "class": "obj",
                "height": 58.95815553031372,
                "id": "toothpaste_0",
                "type": "rect",
                "width": 20.081075170302334,
                "x": 384.6704262182413,
                "y": 177.85945125167152
            },
            {
                "class": "obj",
                "height": 53.87785243628625,
                "id": "kleenex_0",
                "type": "rect",
                "width": 71.87800088669061,
                "x": 320,
                "y": 175
            },
            {
                "class": "obj",
                "height": 67.00865419505942,
                "id": "greens_1",
                "type": "rect",
                "width": 205.87578737089652,
                "x": 217,
                "y": 255
            },
            {
                "class": "obj",
                "height": 42.15694143075166,
                "id": "flashlight_0",
                "type": "rect",
                "width": 65.69636908409564,
                "x": 273,
                "y": 327
            },
            {
                "class": "obj",
                "height": 26.157250650019876,
                "id": "rubber_eraser_1",
                "type": "rect",
                "width": 30.419978772907328,
                "x": 280,
                "y": 401
            },
            {
                "class": "obj",
                "height": 34.86223396423719,
                "id": "cap_0",
                "type": "rect",
                "width": 64.0374034520249,
                "x": 317.56219499331394,
                "y": 153.28109749665694
            },
            {
                "class": "obj",
                "height": 48.107095749117775,
                "id": "notebook_2",
                "type": "rect",
                "width": 115.78527031074822,
                "x": 258.40548748328484,
                "y": 217
            },
            {
                "class": "obj",
                "height": 20.168445133658253,
                "id": "marker_1",
                "type": "rect",
                "width": 43.222171381012146,
                "x": 266,
                "y": 214
            },
            {
                "class": "obj",
                "height": 15.018755853054074,
                "id": "toothbrush_0",
                "type": "rect",
                "width": 31.567887498646442,
                "x": 303.20822067667194,
                "y": 179.69146508691858
            },
            {
                "class": "obj",
                "height": 28.194042032256903,
                "id": "hand_towel_0",
                "type": "rect",
                "width": 70.664014675358,
                "x": 231.98384123829942,
                "y": 169
            },
            {
                "class": "obj",
                "height": 17.886233712283627,
                "id": "camera_1",
                "type": "rect",
                "width": 32.009977431813596,
                "x": 292,
                "y": 193
            },
            {
                "class": "obj",
                "height": 13.081695391879464,
                "id": "scissors_2",
                "type": "rect",
                "width": 63.61671527776129,
                "x": 215.38932872158432,
                "y": 216.14054874832846
            },
            {
                "class": "obj",
                "height": 23.105823948060873,
                "id": "calculator_1",
                "type": "rect",
                "width": 59.03452377499809,
                "x": 200.70274374164242,
                "y": 225.00000000000003
            },
            {
                "class": "obj",
                "height": 25.413802013037355,
                "id": "notebook_1",
                "type": "rect",
                "width": 101.29229228136714,
                "x": 188.79481620486922,
                "y": 194.9353649531977
            }
        ],
        "class": "image",
        "filename": "img/014.png"
    },
    {
        "annotations": [
            {
                "class": "obj",
                "height": 105.52494480411372,
                "id": "notebook_0",
                "type": "rect",
                "width": 133.57567263771534,
                "x": 471.4411500668963,
                "y": 305.48517530103317
            },
            {
                "class": "obj",
                "height": 102.96765642545105,
                "id": "cereal_box_0",
                "type": "rect",
                "width": 77.0263791868269,
                "x": 435.1176998662075,
                "y": 156.83827489965563
            },
            {
                "class": "obj",
                "height": 53.42104052049953,
                "id": "keyboard_2",
                "type": "rect",
                "width": 135.840008859445,
                "x": 373.5588499331038,
                "y": 235.7205750334481
            },
            {
                "class": "obj",
                "height": 42.347338849827,
                "id": "camera_0",
                "type": "rect",
                "width": 60.795696967452656,
                "x": 385,
                "y": 349
            },
            {
                "class": "obj",
                "height": 42.730362342604394,
                "id": "flashlight_1",
                "type": "rect",
                "width": 25.050908531419225,
                "x": 518.235399732415,
                "y": 274.51482469896683
            },
            {
                "class": "obj",
                "height": 58.95815553031372,
                "id": "toothpaste_0",
                "type": "rect",
                "width": 20.081075170302334,
                "x": 410,
                "y": 179
            },
            {
                "class": "obj",
                "height": 53.87785243628625,
                "id": "kleenex_0",
                "type": "rect",
                "width": 71.87800088669061,
                "x": 345,
                "y": 175
            },
            {
                "class": "obj",
                "height": 68.12635406126685,
                "id": "greens_1",
                "type": "rect",
                "width": 203.36096267192968,
                "x": 245.63252456517432,
                "y": 255.55884993310377
            },
            {
                "class": "obj",
                "height": 42.15694143075166,
                "id": "flashlight_0",
                "type": "rect",
                "width": 65.69636908409564,
                "x": 297,
                "y": 327
            },
            {
                "class": "obj",
                "height": 26.157250650019876,
                "id": "rubber_eraser_1",
                "type": "rect",
                "width": 30.419978772907328,
                "x": 303,
                "y": 400
            },
            {
                "class": "obj",
                "height": 34.86223396423719,
                "id": "cap_0",
                "type": "rect",
                "width": 64.0374034520249,
                "x": 343.7101803904501,
                "y": 153.64490980477504
            },
            {
                "class": "obj",
                "height": 48.107095749117775,
                "id": "notebook_2",
                "type": "rect",
                "width": 115.78527031074822,
                "x": 283,
                "y": 217
            },
            {
                "class": "obj",
                "height": 18.39299415753328,
                "id": "marker_1",
                "type": "rect",
                "width": 41.68344720170384,
                "x": 293.0121777729416,
                "y": 215.53872417930828
            },
            {
                "class": "obj",
                "height": 15.96566304032072,
                "id": "toothbrush_0",
                "type": "rect",
                "width": 31.212797303421453,
                "x": 329.1836339840833,
                "y": 178.57963921910002
            },
            {
                "class": "obj",
                "height": 27.720588438623565,
                "id": "hand_towel_0",
                "type": "rect",
                "width": 67.46820291833299,
                "x": 259.4856313665749,
                "y": 167.57963921910002
            },
            {
                "class": "obj",
                "height": 17.886233712283627,
                "id": "camera_1",
                "type": "rect",
                "width": 30.70798004932199,
                "x": 320.0774483586166,
                "y": 193.11836339840832
            },
            {
                "class": "obj",
                "height": 13.081695391879464,
                "id": "scissors_2",
                "type": "rect",
                "width": 63.61671527776129,
                "x": 241.42036078090007,
                "y": 214.88163660159165
            },
            {
                "class": "obj",
                "height": 21.103115246991905,
                "id": "calculator_1",
                "type": "rect",
                "width": 58.70073899148659,
                "x": 226.3337847835115,
                "y": 225.00270870106897
            },
            {
                "class": "obj",
                "height": 24.703621622587377,
                "id": "notebook_1",
                "type": "rect",
                "width": 98.92502431320051,
                "x": 214.0,
                "y": 192.93472941432498
            }
        ],
        "class": "image",
        "filename": "img/015.png"
    },
    {
        "annotations": [
            {
                "class": "obj",
                "height": 111.38829960141499,
                "id": "notebook_0",
                "type": "rect",
                "width": 139.42222571036893,
                "x": 496.2353182723756,
                "y": 308.4114990038683
            },
            {
                "class": "obj",
                "height": 106.02679396633391,
                "id": "cereal_box_0",
                "type": "rect",
                "width": 79.14424363820741,
                "x": 463.05913754088283,
                "y": 158.0587269104976
            },
            {
                "class": "obj",
                "height": 58.36272424038728,
                "id": "keyboard_2",
                "type": "rect",
                "width": 139.36978294507907,
                "x": 400.64722790662927,
                "y": 235.64681727624395
            },
            {
                "class": "obj",
                "height": 42.347338849827,
                "id": "camera_0",
                "type": "rect",
                "width": 60.795696967452656,
                "x": 410,
                "y": 352
            },
            {
                "class": "obj",
                "height": 43.01145983926142,
                "id": "flashlight_1",
                "type": "rect",
                "width": 25.33200602807625,
                "x": 547.1899496784794,
                "y": 279.9550420364891
            },
            {
                "class": "obj",
                "height": 58.95815553031372,
                "id": "toothpaste_0",
                "type": "rect",
                "width": 20.081075170302334,
                "x": 439.9416837198878,
                "y": 181.2353182723756
            },
            {
                "class": "obj",
                "height": 56.46635343241789,
                "id": "kleenex_0",
                "type": "rect",
                "width": 71.87800088669061,
                "x": 373.529774085634,
                "y": 175.29404518287322
            },
            {
                "class": "obj",
                "height": 68.36167233364245,
                "id": "greens_1",
                "type": "rect",
                "width": 205.00819057855895,
                "x": 271,
                "y": 257
            },
            {
                "class": "obj",
                "height": 42.15694143075166,
                "id": "flashlight_0",
                "type": "rect",
                "width": 65.69636908409564,
                "x": 322,
                "y": 327
            },
            {
                "class": "obj",
                "height": 26.157250650019876,
                "id": "rubber_eraser_1",
                "type": "rect",
                "width": 30.419978772907328,
                "x": 326,
                "y": 400
            },
            {
                "class": "obj",
                "height": 34.86223396423719,
                "id": "cap_0",
                "type": "rect",
                "width": 64.0374034520249,
                "x": 370.6472279066292,
                "y": 154.2940451828732
            },
            {
                "class": "obj",
                "height": 48.107095749117775,
                "id": "notebook_2",
                "type": "rect",
                "width": 115.78527031074822,
                "x": 308,
                "y": 218
            },
            {
                "class": "obj",
                "height": 18.39299415753328,
                "id": "marker_1",
                "type": "rect",
                "width": 41.68344720170384,
                "x": 318,
                "y": 216
            },
            {
                "class": "obj",
                "height": 17.030933625995715,
                "id": "toothbrush_0",
                "type": "rect",
                "width": 31.686250897054734,
                "x": 356.4802822556497,
                "y": 178.96346668117505
            },
            {
                "class": "obj",
                "height": 27.249951893872378,
                "id": "hand_towel_0",
                "type": "rect",
                "width": 70.99797700396707,
                "x": 285.64722790662927,
                "y": 167.2940451828732
            },
            {
                "class": "obj",
                "height": 17.886233712283627,
                "id": "camera_1",
                "type": "rect",
                "width": 30.70798004932199,
                "x": 346.3019973824916,
                "y": 192.64490980477504
            },
            {
                "class": "obj",
                "height": 13.555148985512801,
                "id": "scissors_2",
                "type": "rect",
                "width": 61.841264301636286,
                "x": 269.0774483586167,
                "y": 213.99999999999997
            },
            {
                "class": "obj",
                "height": 21.103115246991905,
                "id": "calculator_1",
                "type": "rect",
                "width": 59.529282780344914,
                "x": 252.65708757771665,
                "y": 224.47345359363334
            },
            {
                "class": "obj",
                "height": 26.715799395529018,
                "id": "notebook_1",
                "type": "rect",
                "width": 96.91284654025887,
                "x": 241.72235816339162,
                "y": 190.57963921910002
            }
        ],
        "class": "image",
        "filename": "img/016.png"
    },
    {
        "annotations": [
            {
                "class": "obj",
                "height": 111.38829960141499,
                "id": "notebook_0",
                "type": "rect",
                "width": 130.53333682148013,
                "x": 509.8888888888888,
                "y": 310.0
            },
            {
                "class": "obj",
                "height": 105.63044649604757,
                "id": "cereal_box_0",
                "type": "rect",
                "width": 82.31502340049816,
                "x": 479,
                "y": 160
            },
            {
                "class": "obj",
                "height": 58.759071710673624,
                "id": "keyboard_2",
                "type": "rect",
                "width": 140.55882535593804,
                "x": 414.810957589141,
                "y": 237.60365252971366
            },
            {
                "class": "obj",
                "height": 38.80143602428376,
                "id": "camera_0",
                "type": "rect",
                "width": 60.795696967452656,
                "x": 422.0,
                "y": 354
            },
            {
                "class": "obj",
                "height": 43.01145983926142,
                "id": "flashlight_1",
                "type": "rect",
                "width": 25.33200602807625,
                "x": 563,
                "y": 283
            },
            {
                "class": "obj",
                "height": 58.95815553031372,
                "id": "toothpaste_0",
                "type": "rect",
                "width": 20.081075170302334,
                "x": 455,
                "y": 182
            },
            {
                "class": "obj",
                "height": 57.85356957842009,
                "id": "kleenex_0",
                "type": "rect",
                "width": 72.07617462183376,
                "x": 389.7926949405727,
                "y": 175.60365252971366
            },
            {
                "class": "obj",
                "height": 68.75801980392879,
                "id": "greens_1",
                "type": "rect",
                "width": 203.62097443255678,
                "x": 286.7835636162885,
                "y": 258.9908686757159
            },
            {
                "class": "obj",
                "height": 38.19346672788828,
                "id": "flashlight_0",
                "type": "rect",
                "width": 63.91280546780712,
                "x": 335,
                "y": 330.9634747028634
            },
            {
                "class": "obj",
                "height": 26.157250650019876,
                "id": "rubber_eraser_1",
                "type": "rect",
                "width": 30.419978772907328,
                "x": 337,
                "y": 400
            },
            {
                "class": "obj",
                "height": 34.86223396423719,
                "id": "cap_0",
                "type": "rect",
                "width": 64.0374034520249,
                "x": 387,
                "y": 155
            },
            {
                "class": "obj",
                "height": 48.107095749117775,
                "id": "notebook_2",
                "type": "rect",
                "width": 115.78527031074822,
                "x": 322,
                "y": 218
            },
            {
                "class": "obj",
                "height": 16.499074853816012,
                "id": "marker_1",
                "type": "rect",
                "width": 39.88920786134011,
                "x": 334.6913590105456,
                "y": 215.9003200366465
            },
            {
                "class": "obj",
                "height": 17.030933625995715,
                "id": "toothbrush_0",
                "type": "rect",
                "width": 31.686250897054734,
                "x": 373,
                "y": 180
            },
            {
                "class": "obj",
                "height": 26.352832223690513,
                "id": "hand_towel_0",
                "type": "rect",
                "width": 67.5091782865932,
                "x": 302.1961595602425,
                "y": 167.59807978012125
            },
            {
                "class": "obj",
                "height": 17.78655374893009,
                "id": "camera_1",
                "type": "rect",
                "width": 29.013420672311796,
                "x": 363.2926391571314,
                "y": 193.0
            },
            {
                "class": "obj",
                "height": 12.857389242038039,
                "id": "scissors_2",
                "type": "rect",
                "width": 59.747985071212,
                "x": 283.99679963353543,
                "y": 215.0964795968889
            },
            {
                "class": "obj",
                "height": 18.212396309739262,
                "id": "calculator_1",
                "type": "rect",
                "width": 56.0404840629711,
                "x": 269.39231912048484,
                "y": 225.295839523596
            },
            {
                "class": "obj",
                "height": 26.715799395529018,
                "id": "notebook_1",
                "type": "rect",
                "width": 96.91284654025887,
                "x": 257,
                "y": 191
            }
        ],
        "class": "image",
        "filename": "img/017.png"
    }
]
